primkit/__init__.py
primkit/config.py
primkit/designer/Primer.py
primkit/designer/__init__.py
primkit/tests/PytestTrigger.py
primkit/tests/SeleniumTests.py
primkit/tests/__init__.py
primkit/utils/DataFetcher.py
primkit/utils/DatabaseHandler.py
primkit/utils/EmailManager.py
primkit/utils/FileReader.py
primkit/utils/LoggerSetup.py
primkit/utils/ResultDownloader.py
primkit/utils/SeleniumCookies.py
primkit/utils/SiteRequester.py
primkit/utils/SiteSeleniumer.py
primkit/utils/SysProfiler.py
primkit/utils/WebdriverInitializer.py
primkit/utils/__init__.py
primkit-0.1.8.dist-info/LICENSE
primkit-0.1.8.dist-info/METADATA
primkit-0.1.8.dist-info/WHEEL
primkit-0.1.8.dist-info/top_level.txt
primkit-0.1.8.dist-info/RECORD
