Metadata-Version: 2.1
Name: primkit
Version: 0.1.8
Summary: A primer design assistant tool for convenient and efficient primer design and result preprocessing.
Home-page: https://github.com/Enthusiasm23/primkit
Author: LiBao Feng
Author-email: lbfeng23@gmail.com
Project-URL: Documentation, https://primkit.readthedocs.io/
Project-URL: Source, https://github.com/Enthusiasm23/primkit
Project-URL: Tracker, https://github.com/Enthusiasm23/primkit/issues
Classifier: Development Status :: 4 - Beta
Classifier: Intended Audience :: Developers
Classifier: License :: OSI Approved :: MIT License
Classifier: Programming Language :: Python :: 3
Classifier: Operating System :: OS Independent
Requires-Python: >=3.6
License-File: LICENSE
Requires-Dist: beautifulsoup4 (<5.0,>=4.10.0)
Requires-Dist: fake-useragent (<2.0,>=1.4.0)
Requires-Dist: IMAPClient (<3.0,>=2.3.0)
Requires-Dist: numpy (<2.0,>=1.21.0)
Requires-Dist: pandas (<2.2,>=1.0.0)
Requires-Dist: Requests (<3.0,>=2.20)
Requires-Dist: selenium (<5.0,>=4.0.0)
Requires-Dist: SQLAlchemy (<2.1,>=2.0)
Requires-Dist: SQLAlchemy-Utils (<0.42.0,>=0.40.0)
Requires-Dist: tqdm (<5.0,>=4.60)
Requires-Dist: urllib3 (<1.27,>=1.25.0)
Requires-Dist: webdriver-manager (<5.0,>=4.0.0)
Requires-Dist: yagmail (<0.16.0,>=0.15.0)
Requires-Dist: pymysql (<2.0,>=1.0.0)
Provides-Extra: dev
Requires-Dist: check-manifest ; extra == 'dev'
Provides-Extra: test
Requires-Dist: coverage ; extra == 'test'
